osrt/example.py
osrt/libosrt.abi3.so
osrt/__init__.py
osrt/model/threshold_guess.py
osrt/model/tree_regressor.py
osrt/model/__init__.py
osrt/model/encoder.py
osrt/model/osrt.py
osrt/model/imbalance/osdt_imb_v9.py
osrt/model/imbalance/osdt_sup.py
osrt/model/imbalance/__init__.py
osrt/model/imbalance/rule.py
osrt-0.1.8.dist-info/LICENSE
osrt-0.1.8.dist-info/METADATA
osrt-0.1.8.dist-info/top_level.txt
osrt-0.1.8.dist-info/RECORD
osrt-0.1.8.dist-info/WHEEL
