Metadata-Version: 2.1
Name: osrt
Version: 0.1.8
Summary: Implementation of Optimal Sparse Regression Trees
Home-page: https://github.com/ruizhang1996/optimal-sparse-regression-tree-public
Author: UBC Systopia Research Lab
License: BSD 3-Clause
Platform: UNKNOWN
Requires-Python: >=3.9
License-File: LICENSE
Requires-Dist: setuptools
Requires-Dist: wheel
Requires-Dist: attrs
Requires-Dist: packaging>=20.9
Requires-Dist: pandas
Requires-Dist: scikit-learn
Requires-Dist: sortedcontainers
Requires-Dist: gmpy2
Requires-Dist: matplotlib
Requires-Dist: editables==0.2; python_version > "3.0"
